orange_firstcycling-0.1.0.dist-info/licenses/LICENSE
tests/__init__.py
tests/test_rider_search.py
tests/debug/__init__.py
tests/debug/debug_monuments.py
orange_firstcycling-0.1.0.dist-info/METADATA
orange_firstcycling-0.1.0.dist-info/WHEEL
orange_firstcycling-0.1.0.dist-info/top_level.txt
orange_firstcycling-0.1.0.dist-info/RECORD
