Metadata-Version: 2.4
Name: orange-firstcycling
Version: 0.1.0
Summary: FirstCycling MCP server for accessing professional cycling data
Home-page: 
Author: orange
Author-email: support@orange.ai
Requires-Python: >=3.6
License-File: LICENSE
Requires-Dist: httpx>=0.28.1
Requires-Dist: mcp[cli]>=1.5.0
Requires-Dist: beautifulsoup4
Requires-Dist: lxml
Requires-Dist: numpy
Requires-Dist: pandas
Requires-Dist: python-dateutil
Requires-Dist: pytz
Requires-Dist: requests
Requires-Dist: slumber
Requires-Dist: soupsieve
Dynamic: author
Dynamic: author-email
Dynamic: license-file
Dynamic: requires-python
